LICENSE
README.md
setup.cfg
setup.py
pt_lightning_sphinx_theme/__init__.py
pt_lightning_sphinx_theme/breadcrumbs.html
pt_lightning_sphinx_theme/cookie_banner.html
pt_lightning_sphinx_theme/fonts.html
pt_lightning_sphinx_theme/footer.html
pt_lightning_sphinx_theme/layout.html
pt_lightning_sphinx_theme/search.html
pt_lightning_sphinx_theme/searchbox.html
pt_lightning_sphinx_theme/theme.conf
pt_lightning_sphinx_theme/theme_variables.jinja
pt_lightning_sphinx_theme/versions.html
pt_lightning_sphinx_theme.egg-info/PKG-INFO
pt_lightning_sphinx_theme.egg-info/SOURCES.txt
pt_lightning_sphinx_theme.egg-info/dependency_links.txt
pt_lightning_sphinx_theme.egg-info/entry_points.txt
pt_lightning_sphinx_theme.egg-info/not-zip-safe
pt_lightning_sphinx_theme.egg-info/requires.txt
pt_lightning_sphinx_theme.egg-info/top_level.txt
pt_lightning_sphinx_theme/extensions/__init__.py
pt_lightning_sphinx_theme/extensions/lightning.py
pt_lightning_sphinx_theme/extensions/pytorch_tutorials.py
pt_lightning_sphinx_theme/static/css/theme.css
pt_lightning_sphinx_theme/static/fonts/FreightSans/freight-sans-bold-italic.woff
pt_lightning_sphinx_theme/static/fonts/FreightSans/freight-sans-bold-italic.woff2
pt_lightning_sphinx_theme/static/fonts/FreightSans/freight-sans-bold.woff
pt_lightning_sphinx_theme/static/fonts/FreightSans/freight-sans-bold.woff2
pt_lightning_sphinx_theme/static/fonts/FreightSans/freight-sans-book-italic.woff
pt_lightning_sphinx_theme/static/fonts/FreightSans/freight-sans-book-italic.woff2
pt_lightning_sphinx_theme/static/fonts/FreightSans/freight-sans-book.woff
pt_lightning_sphinx_theme/static/fonts/FreightSans/freight-sans-book.woff2
pt_lightning_sphinx_theme/static/fonts/FreightSans/freight-sans-light-italic.woff
pt_lightning_sphinx_theme/static/fonts/FreightSans/freight-sans-light-italic.woff2
pt_lightning_sphinx_theme/static/fonts/FreightSans/freight-sans-light.woff
pt_lightning_sphinx_theme/static/fonts/FreightSans/freight-sans-light.woff2
pt_lightning_sphinx_theme/static/fonts/FreightSans/freight-sans-medium-italic.woff
pt_lightning_sphinx_theme/static/fonts/FreightSans/freight-sans-medium-italic.woff2
pt_lightning_sphinx_theme/static/fonts/FreightSans/freight-sans-medium.woff
pt_lightning_sphinx_theme/static/fonts/FreightSans/freight-sans-medium.woff2
